scattered/__init__.py
scattered-0.0.0.dist-info/METADATA
scattered-0.0.0.dist-info/WHEEL
scattered-0.0.0.dist-info/entry_points.txt
scattered-0.0.0.dist-info/RECORD
